legacy_api_wrap/__init__.py
legacy_api_wrap/py.typed
testing/legacy_api_wrap/__init__.py
testing/legacy_api_wrap/py.typed
testing/legacy_api_wrap/pytest.py
legacy_api_wrap-1.3.dist-info/METADATA
legacy_api_wrap-1.3.dist-info/WHEEL
legacy_api_wrap-1.3.dist-info/licenses/LICENSE
legacy_api_wrap-1.3.dist-info/RECORD
