Metadata-Version: 2.1
Name: legacy-api-wrap
Version: 1.3
Project-URL: Source, https://github.com/flying-sheep/legacy-api-wrap
Author-email: "Philipp A." <flying-sheep@web.de>
License-Expression: GPL-3.0-or-later
License-File: LICENSE
Classifier: Development Status :: 5 - Production/Stable
Classifier: Intended Audience :: Developers
Classifier: Programming Language :: Python :: 3
Classifier: Topic :: Software Development :: Libraries :: Python Modules
Requires-Python: >=3.8
Provides-Extra: test
Requires-Dist: coverage; extra == 'test'
Requires-Dist: coverage-rich; extra == 'test'
Requires-Dist: pytest; extra == 'test'
Requires-Dist: toml; extra == 'test'
